usefathom/__init__.py
usefathom/api.py
usefathom/apps.py
usefathom/context_processors.py
usefathom/templates/usefathom/click.html
usefathom/templates/usefathom/submit.html
usefathom/templates/usefathom/usefathom.html
usefathom/templatetags/fathom.py
usefathom/tests.py
django_usefathom-2.0.3.dist-info/LICENSE
django_usefathom-2.0.3.dist-info/METADATA
django_usefathom-2.0.3.dist-info/WHEEL
django_usefathom-2.0.3.dist-info/RECORD
