Metadata-Version: 2.1
Name: django-usefathom
Version: 2.0.3
Summary: A Django app to integrate Fathom Analytics into your project
Home-page: https://github.com/paulchubatyy/django-usefathom
License: MIT
Author: Paul Chubatyy
Author-email: xobb@citylance.biz
Requires-Python: >=3.9,<4.0
Classifier: License :: OSI Approved :: MIT License
Classifier: Programming Language :: Python :: 3
Classifier: Programming Language :: Python :: 3.9
Classifier: Programming Language :: Python :: 3.10
Classifier: Programming Language :: Python :: 3.11
Classifier: Programming Language :: Python :: 3.12
Project-URL: Repository, https://github.com/paulchubatyy/django-usefathom
